llama_index/embeddings/opea/__init__.py
llama_index/embeddings/opea/base.py
llama_index_embeddings_opea-0.2.2.dist-info/METADATA
llama_index_embeddings_opea-0.2.2.dist-info/WHEEL
llama_index_embeddings_opea-0.2.2.dist-info/licenses/LICENSE
llama_index_embeddings_opea-0.2.2.dist-info/RECORD
